[
    {
        "Australia": [
            "Australian National University (ANU)",
            "University of Melbourne",
            "University of Sydney",
            "University of New South Wales (UNSW Sydney)",
            "University of Queensland (UQ)",
            "Monash University",
            "University of Western Australia (UWA)",
            "University of Adelaide",
            "University of Technology Sydney (UTS)",
            "University of Canberra",
            "Macquarie University",
            "RMIT University",
            "Curtin University",
            "University of Wollongong",
            "Queensland University of Technology (QUT)",
            "Deakin University",
            "Griffith University",
            "University of Newcastle",
            "Western Sydney University",
            "University of Tasmania"
        ]
    },
    {
        "USA": [
            "Massachusetts Institute of Technology (MIT)",
            "Stanford University",
            "Harvard University",
            "California Institute of Technology (Caltech)",
            "University of Chicago",
            "Princeton University",
            "Columbia University",
            "Yale University",
            "University of Pennsylvania",
            "University of California, Berkeley",
            "University of California, Los Angeles (UCLA)",
            "University of Michigan, Ann Arbor",
            "Cornell University",
            "Johns Hopkins University",
            "Northwestern University",
            "University of Washington",
            "Duke University",
            "University of California, San Diego (UCSD)",
            "New York University (NYU)",
            "University of Wisconsin-Madison"
        ]
    },
    {
        "Canada": [
            "University of Toronto",
            "University of British Columbia",
            "McGill University",
            "McMaster University",
            "University of Alberta",
            "University of Waterloo",
            "Western University",
            "University of Calgary",
            "Queen's University",
            "Simon Fraser University",
            "Dalhousie University",
            "University of Manitoba",
            "University of Victoria",
            "York University",
            "Carleton University",
            "University of Guelph",
            "Concordia University"
        ]
    },
    {
        "Ireland": [
            "Trinity College Dublin (TCD)",
            "University College Dublin (UCD)",
            "National University of Ireland, Galway (NUI Galway)",
            "University College Cork (UCC)",
            "Dublin City University (DCU)",
            "University of Limerick (UL)",
            "Maynooth University",
            "Technological University Dublin (TU Dublin)",
            "Royal College of Surgeons in Ireland (RCSI)",
            "Dublin Institute of Technology (now part of TU Dublin)",
            "National College of Ireland (NCI)",
            "Griffith College Dublin",
            "Institute of Technology, Carlow",
            "Waterford Institute of Technology (now part of Technological University of the South East)",
            "Cork Institute of Technology (now part of Munster Technological University)",
            "Limerick Institute of Technology (now part of Technological University of the Shannon: Midlands Midwest)",
            "Dundalk Institute of Technology (DKIT)",
            "Galway-Mayo Institute of Technology (now part of Atlantic Technological University)",
            "Athlone Institute of Technology (now part of Technological University of the Shannon: Midlands Midwest)"
        ]
    },
    {
        "UK": [
            "University of Oxford",
            "University of Cambridge",
            "Imperial College London",
            "London School of Economics and Political Science (LSE)",
            "University College London (UCL)",
            "University of Edinburgh",
            "King's College London",
            "University of Bristol",
            "University of Warwick",
            "University of Glasgow",
            "University of Birmingham",
            "University of Leeds",
            "University of Sheffield",
            "University of Nottingham",
            "University of St Andrews",
            "University of Southampton",
            "University of York",
            "Durham University",
            "Queen Mary University of London"
        ]
    }
]